[
  {
    "data": "2005-01-01",
    "valor": 0.8
  },
  {
    "data": "2005-02-01",
    "valor": 0.51
  },
  {
    "data": "2005-03-01",
    "valor": 0.66
  },
  {
    "data": "2005-04-01",
    "valor": 0.8
  },
  {
    "data": "2005-05-01",
    "valor": 1.02
  },
  {
    "data": "2005-06-01",
    "valor": 0.05
  },
  {
    "data": "2005-07-01",
    "valor": 0.12
  },
  {
    "data": "2005-08-01",
    "valor": -0.32
  },
  {
    "data": "2005-09-01",
    "valor": -0.17
  },
  {
    "data": "2005-10-01",
    "valor": 0.42
  },
  {
    "data": "2005-11-01",
    "valor": 0.46
  },
  {
    "data": "2005-12-01",
    "valor": 0.52
  }
]