[
  {
    "data": "1977-01-01",
    "valor": 3.62
  },
  {
    "data": "1977-02-01",
    "valor": 3.99
  },
  {
    "data": "1977-03-01",
    "valor": 4.8
  },
  {
    "data": "1977-04-01",
    "valor": 4.43
  },
  {
    "data": "1977-05-01",
    "valor": 2.16
  },
  {
    "data": "1977-06-01",
    "valor": 2.57
  },
  {
    "data": "1977-07-01",
    "valor": 1.93
  },
  {
    "data": "1977-08-01",
    "valor": 1.57
  },
  {
    "data": "1977-09-01",
    "valor": 1.99
  },
  {
    "data": "1977-10-01",
    "valor": 2.26
  },
  {
    "data": "1977-11-01",
    "valor": 2.86
  },
  {
    "data": "1977-12-01",
    "valor": 2.8
  }
]